{
  "$comment": "Stacklands (v1.4.1.21)",
  "type": "object",
  "allOf": [
    {
      "type": "object",
      "properties": {
        "$schema": {
          "type": "string"
        },
        "id": {
          "type": "string"
        },
        "nameTerm": {
          "$ref": "#/$defs/term"
        },
        "nameOverride": {
          "type": "string"
        },
        "minQuestCount": {
          "type": "integer"
        },
        "cost": {
          "type": "integer"
        },
        "icon": {
          "type": "string",
          "description": "Sprite. Value must be the file name of an image in your mods Icons/ folder."
        },
        "location": {
          "$ref": "#/$defs/enum/Location"
        },
        "cardBags": {
          "type": "array",
          "items": {
            "$ref": "#/$defs/typeCardBag"
          }
        }
      },
      "required": [
        "id"
      ]
    },
    {
      "oneOf": [
        {
          "required": [
            "nameTerm"
          ]
        },
        {
          "required": [
            "nameOverride"
          ]
        }
      ]
    }
  ],
  "$defs": {
    "typeColor": {
      "type": "string",
      "pattern": "^((#[0-9A-Fa-f]{8})|(#[0-9A-Fa-f]{6})|(#[0-9A-Fa-f]{4})|(#[0-9A-Fa-f]{3}))$"
    },
    "typeCardPalette": {
      "type": "object",
      "properties": {
        "Color": {
          "$ref": "#/$defs/typeColor"
        },
        "Color2": {
          "$ref": "#/$defs/typeColor"
        },
        "Icon": {
          "$ref": "#/$defs/typeColor"
        }
      }
    },
    "typeCombatStats": {
      "type": "object",
      "properties": {
        "MaxHealth": {
          "type": "integer"
        },
        "AttackSpeed": {
          "type": "number"
        },
        "HitChance": {
          "type": "number"
        },
        "AttackDamage": {
          "type": "integer"
        },
        "Defence": {
          "type": "integer"
        },
        "AttackSpeedIncrement": {
          "type": "integer"
        },
        "HitChanceIncrement": {
          "type": "integer"
        },
        "AttackDamageIncrement": {
          "type": "integer"
        },
        "DefenceIncrement": {
          "type": "integer"
        }
      }
    },
    "typeBaitBag": {
      "type": "object",
      "properties": {
        "baitId": {
          "type": "string"
        }
      }
    },
    "typeCardChance": {
      "allOf": [
        {
          "properties": {
            "Id": {
              "$ref": "#/$defs/cardId"
            },
            "Chance": {
              "type": "integer"
            },
            "HasMaxCount": {
              "type": "boolean"
            },
            "HasPrerequisiteCard": {
              "type": "boolean"
            },
            "IsEnemy": {
              "type": "boolean"
            }
          }
        },
        {
          "if": {
            "properties": {
              "HasPrerequisiteCard": {
                "const": true
              }
            },
            "required": [
              "HasPrerequisiteCard"
            ]
          },
          "then": {
            "properties": {
              "PrerequisiteCardId": {
                "$ref": "#/$defs/cardId"
              }
            }
          }
        },
        {
          "if": {
            "allOf": [
              {
                "properties": {
                  "HasMaxCount": {
                    "const": true
                  }
                },
                "required": [
                  "HasMaxCount"
                ]
              },
              {
                "not": {
                  "properties": {
                    "IsEnemy": {
                      "const": true
                    }
                  },
                  "required": [
                    "IsEnemy"
                  ]
                }
              }
            ]
          },
          "then": {
            "properties": {
              "MaxCountToGive": {
                "type": "integer"
              }
            }
          }
        },
        {
          "if": {
            "properties": {
              "IsEnemy": {
                "const": true
              }
            },
            "required": [
              "IsEnemy"
            ]
          },
          "then": {
            "properties": {
              "EnemyBag": {
                "$ref": "#/$defs/enum/EnemySetCardBag"
              },
              "Strength": {
                "type": "number"
              }
            }
          }
        }
      ]
    },
    "typeCardBag": {
      "type": "object",
      "allOf": [
        {
          "properties": {
            "CardBagType": {
              "type": "string"
            }
          }
        },
        {
          "if": {
            "properties": {
              "CardBagType": {
                "const": "Chances"
              }
            },
            "required": [
              "CardBagType"
            ]
          },
          "then": {
            "properties": {
              "Chances": {
                "type": "array",
                "items": {
                  "$ref": "#/$defs/typeCardChance"
                }
              }
            }
          }
        },
        {
          "if": {
            "properties": {
              "CardBagType": {
                "const": "SetPack"
              }
            },
            "required": [
              "CardBagType"
            ]
          },
          "then": {
            "properties": {
              "SetPackCards": {
                "$ref": "#/$defs/cardIdArray"
              }
            }
          }
        },
        {
          "if": {
            "properties": {
              "CardBagType": {
                "const": "SetCardBag"
              }
            },
            "required": [
              "CardBagType"
            ]
          },
          "then": {
            "properties": {
              "SetCardBag": {
                "$ref": "#/$defs/enum/SetCardBagType"
              },
              "UseFallbackBag": {
                "type": "boolean"
              },
              "FallbackBag": {
                "$ref": "#/$defs/enum/SetCardBagType"
              }
            }
          }
        },
        {
          "if": {
            "properties": {
              "CardBagType": {
                "const": "Enemies"
              }
            },
            "required": [
              "CardBagType"
            ]
          },
          "then": {
            "properties": {
              "EnemyCardBag": {
                "$ref": "#/$defs/enum/EnemySetCardBag"
              },
              "StrengthLevel": {
                "type": "number"
              }
            }
          }
        }
      ]
    },
    "typeSubprint": {
      "type": "object",
      "properties": {
        "RequiredCards": {
          "type": "string"
        },
        "CardsToRemove": {
          "type": "string"
        },
        "ResultCard": {
          "$ref": "#/$defs/cardId"
        },
        "ResultAction": {
          "type": "string"
        },
        "ExtraResultCards": {
          "type": "string"
        },
        "Time": {
          "type": "number"
        },
        "StatusTerm": {
          "type": "string"
        },
        "statusOverride": {
          "type": "string"
        }
      }
    },
    "cardId": {
      "type": "string",
      "enum": [
        "chicken",
        "cow",
        "rabbit",
        "blueprint_animalpen",
        "blueprint_brick",
        "blueprint_brickyard",
        "blueprint_campfire",
        "blueprint_carving",
        "blueprint_chicken",
        "blueprint_coinchest",
        "blueprint_cookedmeat",
        "blueprint_farm",
        "blueprint_frittata",
        "blueprint_fruitsalad",
        "blueprint_garden",
        "blueprint_growth",
        "blueprint_house",
        "blueprint_iron_bar",
        "blueprint_lumbercamp",
        "blueprint_market",
        "blueprint_milkshake",
        "blueprint_mine",
        "blueprint_offspring",
        "blueprint_omelette",
        "blueprint_planks",
        "blueprint_quarry",
        "blueprint_sawmill",
        "blueprint_shed",
        "blueprint_smelting",
        "blueprint_woodenweapons",
        "blueprint_stew",
        "blueprint_stove",
        "blueprint_ironweapons",
        "blueprint_temple",
        "blueprint_warehouse",
        "card_display_spirit_dlc",
        "bear",
        "demon",
        "giant_rat",
        "goblin",
        "rat",
        "skeleton",
        "slime",
        "small_slime",
        "wicked_witch",
        "wolf",
        "map",
        "spear",
        "sword",
        "apple",
        "berry",
        "carrot",
        "cooked_meat",
        "egg",
        "frittata",
        "fruit_salad",
        "milk",
        "milkshake",
        "mushroom",
        "omelette",
        "onion",
        "potato",
        "raw_meat",
        "stew",
        "catacombs",
        "forest",
        "graveyard",
        "mountain",
        "old_village",
        "plains",
        "corpse",
        "goblet",
        "kid",
        "bone",
        "brick",
        "flint",
        "gold",
        "iron_bar",
        "iron_ore",
        "key",
        "magic_dust",
        "plank",
        "poop",
        "stick",
        "stone",
        "wood",
        "rumor_combat",
        "rumor_dark_forest",
        "animal_pen",
        "apple_tree",
        "berrybush",
        "brickyard",
        "campfire",
        "coin_chest",
        "farm",
        "garden",
        "house",
        "iron_deposit",
        "lumbercamp",
        "market",
        "mine",
        "old_tome",
        "quarry",
        "rare_portal",
        "rock",
        "sawmill",
        "shed",
        "smelter",
        "smithy",
        "soil",
        "stove",
        "strange_portal",
        "temple",
        "travelling_cart",
        "treasure_chest",
        "tree",
        "warehouse",
        "dog",
        "explorer",
        "militia",
        "swordsman",
        "villager",
        "ideas_island",
        "crab",
        "monkey",
        "parrot",
        "demon_lord",
        "kraken",
        "momma_crab",
        "pirate",
        "seagull",
        "snake",
        "tentacle",
        "tiger",
        "fishing_rod",
        "cod",
        "eel",
        "mackerel",
        "shark",
        "tuna",
        "banana",
        "bottle_of_rum",
        "ceviche",
        "chili_pepper",
        "cooked_crab_meat",
        "cooked_fish",
        "lime",
        "raw_crab_meat",
        "raw_fish",
        "seafood_stew",
        "seaweed",
        "sugar",
        "sushi",
        "tamago_sushi",
        "water",
        "blueprint_aquarium",
        "blueprint_bottle",
        "blueprint_cathedral",
        "blueprint_ceviche",
        "blueprint_charcoal",
        "blueprint_coin",
        "blueprint_composter",
        "blueprint_cooked_crab_meat",
        "blueprint_cooked_fish",
        "blueprint_distillery",
        "blueprint_fabric",
        "blueprint_fill_bottle",
        "blueprint_fishing_rod",
        "blueprint_fish_trap",
        "blueprint_frigate",
        "blueprint_glass",
        "blueprint_gold_bar",
        "blueprint_gold_mine",
        "blueprint_greenhouse",
        "blueprint_mess_hall",
        "blueprint_rope",
        "blueprint_rowboat",
        "blueprint_rum",
        "blueprint_sacred_key",
        "blueprint_sail",
        "blueprint_sand_quarry",
        "blueprint_sandstone",
        "blueprint_seafood_stew",
        "blueprint_shell_chest",
        "blueprint_sloop",
        "blueprint_sushi",
        "blueprint_tamago_sushi",
        "cave",
        "jungle",
        "bottle_of_water",
        "charcoal",
        "cotton",
        "empty_bottle",
        "fabric",
        "glass",
        "gold_bar",
        "gold_ore",
        "goop",
        "island_relic",
        "rope",
        "sacred_chest",
        "sacred_key",
        "sail",
        "sand",
        "sandstone",
        "shell",
        "treasure_map",
        "rumor_eel_bait",
        "rumor_island",
        "rumor_shark_bait",
        "rumor_tuna_bait",
        "aquarium",
        "banana_tree",
        "cathedral",
        "composter",
        "cotton_plant",
        "distillery",
        "driftwood",
        "fishing_spot",
        "fish_trap",
        "frigate",
        "gold_deposit",
        "gold_mine",
        "greenhouse",
        "mess_hall",
        "pirate_boat",
        "rowboat",
        "sand_quarry",
        "shell_chest",
        "sloop",
        "spring",
        "stable_portal",
        "sugar_cane",
        "fisher",
        "friendly_pirate",
        "trained_monkey",
        "blueprint_smithy",
        "blueprint_stable_portal",
        "dark_elf",
        "elf",
        "elf_archer",
        "enchanted_shroom",
        "ent",
        "feral_cat",
        "frog_man",
        "ghost",
        "giant_snail",
        "goblin_archer",
        "goblin_shaman",
        "merman",
        "mimic",
        "mosquito",
        "ogre",
        "orc_wizard",
        "blueprint_chainmail_armor",
        "blueprint_gold_chestplate",
        "blueprint_iron_shield",
        "blueprint_wizard_robe",
        "blueprint_wooden_shield",
        "chainmail_armor",
        "crab_scale_armor",
        "fire_cloak",
        "gold_chestplate",
        "iron_shield",
        "quiver",
        "tiger_fur_coat",
        "leather_tunic",
        "wizard_robe",
        "wooden_shield",
        "blueprint_amulet_of_forest",
        "blueprint_amulet_of_mountain",
        "amulet_of_forest",
        "amulet_of_mountain",
        "bunny_hat",
        "dark_amulet",
        "frog_helmet",
        "goblin_hat",
        "helmet",
        "horned_helmet",
        "pirate_hat",
        "rat_crown",
        "skull_helmet",
        "wolf_head",
        "blueprint_axe",
        "blueprint_blunderbuss",
        "blueprint_bone_spear",
        "blueprint_bone_staff",
        "blueprint_boomerang",
        "blueprint_bow",
        "blueprint_broken_bottle",
        "blueprint_club",
        "blueprint_crossbow",
        "blueprint_hammer",
        "blueprint_magic_blade",
        "blueprint_magic_ring",
        "blueprint_magic_staff",
        "blueprint_magic_tome",
        "blueprint_magic_wand",
        "blueprint_pickaxe",
        "blueprint_slingshot",
        "blueprint_spiked_plank",
        "blueprint_throwing_star",
        "axe",
        "bear_claw",
        "blowpipe",
        "blunderbuss",
        "bone_spear",
        "bone_staff",
        "boomerang",
        "bow",
        "broken_bottle",
        "club",
        "crossbow",
        "demon_sword",
        "hammer",
        "kraken_tooth_axe",
        "magic_blade",
        "magic_broom",
        "magic_ring",
        "magic_staff",
        "magic_tome",
        "magic_wand",
        "morning_star",
        "pickaxe",
        "pirate_sword",
        "slingshot",
        "spiked_plank",
        "staff_of_fear",
        "throwing_star",
        "archer",
        "builder",
        "lumberjack",
        "mage",
        "miner",
        "ninja",
        "warrior",
        "wizard",
        "blueprint_breedingpen",
        "blueprint_conveyor",
        "blueprint_heavy_foundation",
        "blueprint_hotpot",
        "blueprint_lighthouse",
        "blueprint_resourcechest",
        "blueprint_resource_magnet",
        "blueprint_slaughterhouse",
        "blueprint_trash_can",
        "blueprint_university",
        "blueprint_wishing_well",
        "breeding_pen",
        "conveyor",
        "heavy_foundation",
        "hotpot",
        "lighthouse",
        "resource_chest",
        "resource_magnet",
        "slaughter_house",
        "trash_can",
        "university",
        "wishing_well"
      ]
    },
    "cardIdArray": {
      "type": "array",
      "items": {
        "$ref": "#/$defs/cardId"
      }
    },
    "term": {
      "type": "string",
      "enum": [
        "card_animal_pen_description",
        "card_animal_pen_name",
        "card_apple_description",
        "card_apple_name",
        "card_apple_tree_description",
        "card_apple_tree_name",
        "card_apple_tree_status",
        "card_bear_description",
        "card_bear_name",
        "card_berry_description",
        "card_berry_name",
        "card_berrybush_description",
        "card_berrybush_name",
        "card_berrybush_status",
        "card_bone_description",
        "card_bone_name",
        "card_brick_description",
        "card_brick_name",
        "card_brickyard_description",
        "card_brickyard_name",
        "card_campfire_description",
        "card_campfire_name",
        "card_carrot_description",
        "card_carrot_name",
        "card_catacombs_description",
        "card_catacombs_name",
        "card_catacombs_status",
        "card_chicken_description",
        "card_chicken_name",
        "card_cooked_meat_description",
        "card_cooked_meat_name",
        "card_corpse_description",
        "card_corpse_name",
        "card_cow_description",
        "card_cow_name",
        "card_demon_description",
        "card_demon_name",
        "card_dog_description",
        "card_dog_name",
        "card_egg_description",
        "card_egg_name",
        "card_explorer_description",
        "card_explorer_name",
        "card_farm_description",
        "card_farm_name",
        "card_flint_description",
        "card_flint_name",
        "card_forest_description",
        "card_forest_name",
        "card_forest_status",
        "card_frittata_description",
        "card_frittata_name",
        "card_fruit_salad_description",
        "card_fruit_salad_name",
        "card_garden_description",
        "card_garden_name",
        "card_giant_rat_description",
        "card_giant_rat_name",
        "card_goblet_description",
        "card_goblet_name",
        "card_goblin_description",
        "card_goblin_name",
        "card_gold_description",
        "card_gold_name",
        "card_graveyard_description",
        "card_graveyard_name",
        "card_graveyard_status",
        "card_house_description",
        "card_house_name",
        "card_iron_bar_description",
        "card_iron_bar_name",
        "card_iron_deposit_description",
        "card_iron_deposit_name",
        "card_iron_deposit_status",
        "card_iron_ore_description",
        "card_iron_ore_name",
        "card_key_description",
        "card_key_name",
        "card_kid_description",
        "card_kid_name",
        "card_lumbercamp_description",
        "card_lumbercamp_name",
        "card_lumbercamp_status",
        "card_map_description",
        "card_map_name",
        "card_market_name",
        "card_militia_name",
        "card_milk_description",
        "card_milk_name",
        "card_milkshake_description",
        "card_milkshake_name",
        "card_mountain_description",
        "card_mountain_name",
        "card_mountain_status",
        "card_mushroom_description",
        "card_mushroom_name",
        "card_old_tome_description",
        "card_old_tome_name",
        "card_old_tome_status",
        "card_old_village_description",
        "card_old_village_name",
        "card_old_village_status",
        "card_omelette_description",
        "card_omelette_name",
        "card_onion_description",
        "card_onion_name",
        "card_plains_description",
        "card_plains_name",
        "card_plains_status",
        "card_plank_description",
        "card_plank_name",
        "card_poop_description",
        "card_poop_name",
        "card_potato_description",
        "card_potato_name",
        "card_quarry_description",
        "card_quarry_name",
        "card_quarry_status",
        "card_rabbit_description",
        "card_rabbit_name",
        "card_rat_description",
        "card_rat_name",
        "card_raw_meat_description",
        "card_raw_meat_name",
        "card_rock_description",
        "card_rock_name",
        "card_rock_status",
        "card_sawmill_description",
        "card_sawmill_name",
        "card_shed_description",
        "card_shed_name",
        "card_skeleton_description",
        "card_skeleton_name",
        "card_slime_description",
        "card_slime_name",
        "card_small_slime_description",
        "card_small_slime_name",
        "card_soil_description",
        "card_soil_name",
        "card_spear_description",
        "card_spear_name",
        "card_stew_description",
        "card_stew_name",
        "card_stick_description",
        "card_stick_name",
        "card_stone_description",
        "card_stone_name",
        "card_stove_description",
        "card_stove_name",
        "card_sword_description",
        "card_sword_name",
        "card_swordsman_name",
        "card_temple_description",
        "card_temple_name",
        "card_travelling_cart_description",
        "card_travelling_cart_name",
        "card_treasure_chest_description",
        "card_treasure_chest_name",
        "card_tree_description",
        "card_tree_name",
        "card_tree_status",
        "card_villager_description",
        "card_villager_name",
        "card_warehouse_description",
        "card_warehouse_name",
        "card_wolf_description",
        "card_wolf_name",
        "card_wood_description",
        "card_wood_name",
        "cardtype_food",
        "cardtype_ideas",
        "cardtype_locations",
        "cardtype_mobs",
        "cardtype_resources",
        "cardtype_structures",
        "idea_animalpen_status_0",
        "idea_brick_status_0",
        "idea_brickyard_status_0",
        "idea_campfire_status_0",
        "idea_carving_status_0",
        "idea_chicken_status_0",
        "idea_coinchest_status_0",
        "idea_cookedmeat_status_0",
        "idea_farm_status_0",
        "idea_frittata_status_0",
        "idea_fruitsalad_status_0",
        "idea_garden_status_0",
        "idea_growth_name",
        "idea_growth_status_0",
        "idea_growth_status_1",
        "idea_growth_status_2",
        "idea_growth_status_3",
        "idea_growth_status_4",
        "idea_growth_status_5",
        "idea_house_status_0",
        "idea_ironweapons_status_0",
        "idea_ironweapons_status_1",
        "idea_lumbercamp_status_0",
        "idea_market_status_0",
        "idea_milkshake_status_0",
        "idea_mine_status_0",
        "idea_offspring_name",
        "idea_offspring_status_0",
        "idea_offspring_status_1",
        "idea_omelette_status_0",
        "idea_planks_status_0",
        "idea_quarry_status_0",
        "idea_sawmill_status_0",
        "idea_shed_status_0",
        "idea_smelting_status_0",
        "idea_smelting_status_1",
        "idea_stew_status_0",
        "idea_stove_status_0",
        "idea_temple_status_0",
        "idea_warehouse_status_0",
        "idea_woodenweapons_status_0",
        "idea_woodenweapons_status_1",
        "idea_woodenweapons_status_2",
        "ideagroup_basic",
        "ideagroup_building",
        "ideagroup_cooking",
        "ideagroup_military",
        "ideagroup_resources",
        "label_an_idea",
        "label_back",
        "label_back_to_menu",
        "label_buy_packs_to_find_idea",
        "label_cant_be_sold",
        "label_card_not_found",
        "label_cardopedia",
        "label_cards_found",
        "label_cards_infobox",
        "label_cards_infobox_warning",
        "label_clear_save",
        "label_clear_save_confirm",
        "label_click_this_pack",
        "label_coin_infobox_text",
        "label_coin_infobox_title",
        "label_combat_speed",
        "label_complete_more_quests",
        "label_complete_more_quests_for_pack",
        "label_completed_main_quest",
        "label_continue",
        "label_continue_run",
        "label_credits",
        "label_damage",
        "label_drag_coins_to_buy_pack",
        "label_drop_to_sell",
        "label_eating",
        "label_end_of_moon",
        "label_everyone_fed",
        "label_everyone_starved",
        "label_feed_villagers",
        "label_foil",
        "label_fullscreen",
        "label_game_options",
        "label_game_over",
        "label_goblet_brought_to_temple",
        "label_hit_chance",
        "label_idea_fullname",
        "label_ideas",
        "label_ideas_found",
        "label_keep_playing",
        "label_languages_title",
        "label_may_contain",
        "label_moon_length",
        "label_moon_length_long",
        "label_moon_length_normal",
        "label_moon_length_short",
        "label_moon_length_tooltip",
        "label_new",
        "label_new_cards_found",
        "label_new_pack_unlocked",
        "label_new_run_confirm",
        "label_nice",
        "label_no",
        "label_off",
        "label_okay",
        "label_on",
        "label_options",
        "label_pack_now_available",
        "label_paused",
        "label_peaceful_mode",
        "label_peaceful_mode_tooltip",
        "label_quest",
        "label_quest_completed",
        "label_quest_not_possible_in_peaceful",
        "label_quests",
        "label_quests_completed",
        "label_quit",
        "label_resolution",
        "label_resolutions_title",
        "label_seconds_format",
        "label_seconds_left_format",
        "label_select_language",
        "label_sell",
        "label_sell_cards_to_continue",
        "label_sell_x_cards",
        "label_sellbox_title",
        "label_sfx",
        "label_stack_of_cards",
        "label_start_new_moon",
        "label_start_new_run",
        "label_start_of_moon",
        "label_start_run",
        "label_start_the_ritual",
        "label_strange_portal_appeared",
        "label_time_to_eat",
        "label_timetext",
        "label_timetext_peaceful",
        "label_toggle_panel_title",
        "label_too_many_cards",
        "label_travelling_cart_appeared",
        "label_uh_oh",
        "label_undiscovered_cards",
        "label_well_done",
        "label_yes",
        "label_you_killed_the_demon",
        "label_you_reached_moon",
        "pack_a_new_world_text",
        "pack_cuisine_text",
        "pack_explorers_text",
        "pack_farming_text",
        "pack_humble_beginnings_text",
        "pack_logic_reason_text",
        "pack_order_structure_text",
        "pack_seeking_wisdom_text",
        "quest_3_villagers_text",
        "quest_bring_goblet_text",
        "quest_build_3_houses_text",
        "quest_build_farm_text",
        "quest_build_house_text",
        "quest_build_temple_text",
        "quest_buy_booster_text",
        "quest_buy_from_travelling_cart_text",
        "quest_carve_stick_text",
        "quest_cook_frittata_text",
        "quest_cook_meat_text",
        "quest_cook_omelette_text",
        "quest_create_brickyard_text",
        "quest_create_lumbercamp_text",
        "quest_create_offspring_text",
        "quest_create_quarry_text",
        "quest_create_shed_text",
        "quest_explore_forest_text",
        "quest_explore_mountain_text",
        "quest_find_catacombs_text",
        "quest_find_goblet_text",
        "quest_find_graveyard_text",
        "quest_get_a_dog_text",
        "quest_get_iron_bar_text",
        "quest_have_gold_text",
        "quest_have_10_ideas_text",
        "quest_have_10_stone_text",
        "quest_have_10_wood_text",
        "quest_have_food_text",
        "quest_have_5_ideas_text",
        "quest_kill_a_rat_text",
        "quest_kill_a_skeleton_text",
        "quest_kill_demon_text",
        "quest_open_starter_pack_text",
        "quest_open_treasure_chest_text",
        "quest_pick_berrybush_text",
        "quest_reach_month_text",
        "quest_second_villager_text",
        "quest_sell_at_market_text",
        "quest_sell_card_text",
        "quest_start_campfire_text",
        "quest_train_explorer_text",
        "quest_train_militia_text",
        "quest_unlock_all_packs_text",
        "new_creating_graveyard",
        "new_selling_card",
        "new_portal_shaking",
        "new_growing_up",
        "card_aquarium_description",
        "card_aquarium_name",
        "card_banana_description",
        "card_banana_name",
        "card_banana_tree_description",
        "card_banana_tree_name",
        "card_banana_tree_status",
        "card_boat_status",
        "card_bottle_of_rum_description",
        "card_bottle_of_rum_name",
        "card_bottle_of_water_description",
        "card_bottle_of_water_name",
        "card_captain_description",
        "card_captain_name",
        "card_cathedral_description",
        "card_cathedral_name",
        "card_cave_description",
        "card_cave_name",
        "card_cave_status",
        "card_ceviche_description",
        "card_ceviche_name",
        "card_charcoal_description",
        "card_charcoal_name",
        "card_chili_pepper_description",
        "card_chili_pepper_name",
        "card_coconut_description",
        "card_coconut_name",
        "card_coconut_piece_description",
        "card_coconut_piece_name",
        "card_coconut_tree_description",
        "card_coconut_tree_name",
        "card_coconut_tree_status",
        "card_cod_name",
        "card_coin_chest_description",
        "card_coin_chest_description_long",
        "card_coin_chest_name",
        "card_composter_description",
        "card_composter_name",
        "card_cooked_crab_meat_description",
        "card_cooked_crab_meat_name",
        "card_cooked_fish_description",
        "card_cooked_fish_name",
        "card_cotton_description",
        "card_cotton_name",
        "card_cotton_plant_description",
        "card_cotton_plant_name",
        "card_cotton_plant_status",
        "card_crab_description",
        "card_crab_name",
        "card_demon_lord_description",
        "card_demon_lord_name",
        "card_distillery_description",
        "card_distillery_name",
        "card_driftwood_description",
        "card_driftwood_name",
        "card_driftwood_status",
        "card_eel_description",
        "card_eel_name",
        "card_empty_bottle_description",
        "card_empty_bottle_name",
        "card_fabric_description",
        "card_fabric_name",
        "card_fish_trap_description",
        "card_fish_trap_name",
        "card_fish_trap_status",
        "card_fisher_description",
        "card_fisher_name",
        "card_fishing_rod_description",
        "card_fishing_rod_name",
        "card_fishing_spot_description",
        "card_fishing_spot_name",
        "card_fishing_spot_status",
        "card_friendly_pirate_description",
        "card_friendly_pirate_name",
        "card_frigate_description",
        "card_frigate_name",
        "card_glass_description",
        "card_glass_name",
        "card_gold_bar_description",
        "card_gold_bar_name",
        "card_gold_deposit_description",
        "card_gold_deposit_name",
        "card_gold_deposit_status",
        "card_gold_mine_description",
        "card_gold_mine_name",
        "card_gold_mine_status",
        "card_gold_ore_description",
        "card_gold_ore_name",
        "card_goop_description",
        "card_goop_name",
        "card_greenhouse_description",
        "card_greenhouse_name",
        "card_island_relic_description",
        "card_island_relic_name",
        "card_jungle_description",
        "card_jungle_name",
        "card_jungle_status",
        "card_kraken_description",
        "card_kraken_name",
        "card_lime_description",
        "card_lime_name",
        "card_mackerel_name",
        "card_mess_hall_description",
        "card_mess_hall_name",
        "card_message_in_a_bottle_description",
        "card_message_in_a_bottle_name",
        "card_message_in_a_bottle_status",
        "card_mine_description",
        "card_mine_name",
        "card_mine_status",
        "card_momma_crab_description",
        "card_momma_crab_name",
        "card_monkey_description",
        "card_monkey_name",
        "card_parrot_description",
        "card_parrot_name",
        "card_pirate_boat_description",
        "card_pirate_boat_name",
        "card_pirate_boat_status",
        "card_pirate_description",
        "card_pirate_name",
        "card_raw_crab_meat_description",
        "card_raw_crab_meat_name",
        "card_raw_fish_description",
        "card_raw_fish_name",
        "card_rope_description",
        "card_rope_name",
        "card_rowboat_description",
        "card_rowboat_name",
        "card_sacred_chest_description",
        "card_sacred_chest_name",
        "card_sacred_key_description",
        "card_sacred_key_name",
        "card_sail_description",
        "card_sail_name",
        "card_sand_description",
        "card_sand_name",
        "card_sand_quarry_description",
        "card_sand_quarry_name",
        "card_sand_quarry_status",
        "card_sandstone_description",
        "card_sandstone_name",
        "card_seafood_stew_description",
        "card_seafood_stew_name",
        "card_seagull_description",
        "card_seagull_name",
        "card_seaweed_description",
        "card_seaweed_name",
        "card_shark_description",
        "card_shark_name",
        "card_sheep_description",
        "card_sheep_name",
        "card_shell_chest_description",
        "card_shell_chest_description_long",
        "card_shell_chest_name",
        "card_shell_description",
        "card_shell_name",
        "card_sloop_description",
        "card_sloop_name",
        "card_smelter_description",
        "card_smelter_name",
        "card_smelter_status",
        "card_snake_description",
        "card_snake_name",
        "card_sugar_cane_description",
        "card_sugar_cane_name",
        "card_sugar_cane_status",
        "card_sugar_description",
        "card_sugar_name",
        "card_sushi_description",
        "card_sushi_name",
        "card_tamago_sushi_description",
        "card_tamago_sushi_name",
        "card_tentacle_description",
        "card_tentacle_name",
        "card_tiger_description",
        "card_tiger_name",
        "card_trained_monkey_description",
        "card_trained_monkey_name",
        "card_treasure_map_description",
        "card_treasure_map_name",
        "card_treasure_map_status",
        "card_tuna_name",
        "card_wool_description",
        "card_wool_name",
        "cardtype_fish",
        "cardtype_rumors",
        "empty",
        "idea_aquarium_status_0",
        "idea_befriending_pirate_status",
        "idea_bottle_status_0",
        "idea_cathedral_status_0",
        "idea_ceviche_status",
        "idea_charcoal_status",
        "idea_charcoal_status_0",
        "idea_compass_status",
        "idea_composter_status",
        "idea_composting_status",
        "idea_cooked_crab_meat_status_0",
        "idea_cooked_fish_status_0",
        "idea_cracking_coconut_status",
        "idea_distillery_status",
        "idea_eating_charcoal",
        "idea_fabric_status",
        "idea_filling_bottle_of_water",
        "idea_fish_trap_status",
        "idea_fishing_rod_status",
        "idea_frigate_status0",
        "idea_greenhouse_status_0",
        "idea_growth_name_status_10",
        "idea_growth_name_status_9",
        "idea_growth_status_6",
        "idea_growth_status_7",
        "idea_growth_status_8",
        "idea_mess_hall_status",
        "idea_rope_status",
        "idea_rowboat_status0",
        "idea_rum_status",
        "idea_sacred_key_status0",
        "idea_sail_status0",
        "idea_sand_quarry_status",
        "idea_sandstone_status",
        "idea_seafood_stew_status_0",
        "idea_shell_chest_status_0",
        "idea_sloop_status0",
        "idea_smelting_glass_status",
        "idea_smelting_status_2",
        "idea_smelting_status_3",
        "idea_sushi_status",
        "idea_tamago_sushi_status",
        "idea_training_captain_status",
        "idea_training_fisher_status",
        "idea_training_monkey_status",
        "ideagroup_fishing",
        "ideagroup_important",
        "ideagroup_island",
        "ideagroup_sailing",
        "label_a_rumor",
        "label_awakened_something",
        "label_awakened_the_kraken",
        "label_card_cap",
        "label_complete_more_island_quests_for_pack",
        "label_everyone_on_island_dead",
        "label_everyone_on_island_dead_text",
        "label_island_intro_1",
        "label_island_intro_2",
        "label_island_intro_3",
        "label_island_intro_4",
        "label_island_intro_5",
        "label_island_intro_6",
        "label_island_intro_pack_text",
        "label_island_intro_pack_title",
        "label_island_intro_title",
        "label_join_our_discord",
        "label_main_quests",
        "label_momma_crab_appeared_text",
        "label_momma_crab_appeared_title",
        "label_no_ideas_yet",
        "label_one_villager_needs_to_stay",
        "label_pirate_boat_appeared",
        "label_quests_complete_more_to_see",
        "label_return_to_mainland",
        "label_rumor_full",
        "label_sailing_off_title",
        "label_save_game",
        "label_save_games",
        "label_select_save",
        "label_side_quests",
        "label_start_new_save",
        "label_status_effect",
        "label_time",
        "label_you_killed_the_demon_lord",
        "pack_island_advanced_text",
        "pack_island_cooking_text",
        "pack_island_ideas1_text",
        "pack_island_ideas2_text",
        "pack_island_intro_text",
        "pack_island_locations_text",
        "pack_island1_text",
        "pack_island2_text",
        "quest_befriend_a_pirate_text",
        "quest_bribe_pirate_boat_text",
        "quest_build_cathedral_text",
        "quest_build_composter_text",
        "quest_build_fish_trap_text",
        "quest_build_greenhouse_text",
        "quest_build_mess_hall_text",
        "quest_build_rowboat_text",
        "quest_build_sloop_text",
        "quest_catch_a_fish_text",
        "quest_cook_crab_meat_text",
        "quest_crack_coconut_text",
        "quest_cure_poison_text",
        "quest_drunk_villager_text",
        "quest_find_treasure_map_text",
        "quest_find_treasure_text",
        "quest_forge_sacred_key_text",
        "quest_get_2_bananas_text",
        "quest_have_shells_text",
        "quest_island_relic_to_cathedral_text",
        "quest_kill_demon_lord_text",
        "quest_kill_kraken_text",
        "quest_kill_momma_crab_text",
        "quest_make_ceviche_text",
        "quest_make_fish_trap_text",
        "quest_make_glass_text",
        "quest_make_gold_bar_text",
        "quest_make_rope_text",
        "quest_make_rum_text",
        "quest_make_sail_text",
        "quest_make_sandstone_text",
        "quest_make_seafood_stew_text",
        "quest_make_sushi_text",
        "quest_open_message_in_a_bottle_text",
        "quest_open_sacred_chest_text",
        "quest_poisoned_villager_text",
        "quest_punch_driftwood_text",
        "quest_train_a_fisher_text",
        "quest_train_captain_text",
        "quest_unlock_all_island_packs_text",
        "questgroup_building",
        "questgroup_cooking",
        "questgroup_exploration",
        "questgroup_fighting",
        "questgroup_island",
        "questgroup_island_beginnings",
        "questgroup_island_combat",
        "questgroup_island_cooking",
        "questgroup_island_mainquest",
        "questgroup_island_misc",
        "questgroup_mainquest",
        "questgroup_other",
        "questgroup_resources",
        "questgroup_starter",
        "questgroup_survival",
        "rumor_eel_bait_description",
        "rumor_eel_bait_name",
        "rumor_island_description",
        "rumor_island_name",
        "rumor_shark_bait_description",
        "rumor_shark_bait_name",
        "rumor_tuna_bait_description",
        "rumor_tuna_bait_name",
        "statuseffect_drunk_description",
        "statuseffect_drunk_lore",
        "statuseffect_drunk_name",
        "statuseffect_poison_description",
        "statuseffect_poison_lore",
        "statuseffect_poison_name",
        "statuseffect_spoiling_description",
        "statuseffect_spoiling_lore",
        "statuseffect_spoiling_name",
        "statuseffect_stunned_description",
        "statuseffect_stunned_lore",
        "statuseffect_stunned_name",
        "statuseffect_wellfed_description",
        "statuseffect_wellfed_lore",
        "statuseffect_wellfed_name",
        "label_sailing_off_full",
        "language_dutch",
        "language_french",
        "language_german",
        "language_italian",
        "language_polish",
        "language_spanish",
        "credits_aran",
        "credits_lisa",
        "credits_sokpop",
        "credits_local_heroes",
        "credits_special_thanks",
        "label_relic_brought_to_cathedral",
        "label_controls",
        "control_time_1",
        "control_time_2",
        "control_time_3",
        "control_time_pause",
        "control_panel_collapse",
        "control_zoom",
        "control_sell",
        "control_time_toggle",
        "control_pause",
        "control_grab",
        "control_activate_ui",
        "control_move",
        "control_snap_move",
        "control_snap_cards",
        "label_keyboard_mouse",
        "label_controller",
        "label_waiting_for_input",
        "label_sellbox_description",
        "label_toggle_panel_text",
        "label_auto_pause_controller",
        "label_auto_pause_keyboardmouse",
        "label_binding",
        "label_accessibility",
        "language_portuguese",
        "language_chinese",
        "language_japanese",
        "language_korean",
        "label_progress_stored",
        "label_go_to_island_prompt",
        "label_return_to_mainland_prompt",
        "label_not_enough_food_before_sailing",
        "idea_growth_status_11",
        "card_market_description",
        "attackdamage_veryweak",
        "attackdamage_weak",
        "attackdamage_normal",
        "attackdamage_strong",
        "attackdamage_verystrong",
        "attackdamage_extremelystrong",
        "attackspeed_veryslow",
        "attackspeed_slow",
        "attackspeed_normal",
        "attackspeed_fast",
        "attackspeed_veryfast",
        "attackspeed_extremelyfast",
        "card_amulet_of_forest_description",
        "card_amulet_of_forest_name",
        "card_amulet_of_mountain_description",
        "card_amulet_of_mountain_name",
        "card_archer_description",
        "card_archer_name",
        "card_axe_description",
        "card_axe_name",
        "card_bear_claw_description",
        "card_bear_claw_name",
        "card_blowpipe_description",
        "card_blowpipe_name",
        "card_blunderbuss_description",
        "card_blunderbuss_name",
        "card_bone_spear_description",
        "card_bone_spear_name",
        "card_bone_staff_description",
        "card_bone_staff_name",
        "card_boomerang_description",
        "card_boomerang_name",
        "card_bow_description",
        "card_bow_name",
        "card_broken_bottle_description",
        "card_broken_bottle_name",
        "card_builder_description",
        "card_builder_name",
        "card_bunny_hat_description",
        "card_bunny_hat_name",
        "card_chainmail_armor_description",
        "card_chainmail_armor_name",
        "card_club_description",
        "card_club_name",
        "card_crab_scale_armor_description",
        "card_crab_scale_armor_name",
        "card_crossbow_description",
        "card_crossbow_name",
        "card_dark_amulet_description",
        "card_dark_amulet_name",
        "card_dark_elf_description",
        "card_dark_elf_name",
        "card_demon_sword_description",
        "card_demon_sword_name",
        "card_elf_archer_description",
        "card_elf_archer_name",
        "card_elf_description",
        "card_elf_name",
        "card_enchanted_shroom_description",
        "card_enchanted_shroom_name",
        "card_ent_description",
        "card_ent_name",
        "card_feral_cat_description",
        "card_feral_cat_name",
        "card_fire_cloak_description",
        "card_fire_cloak_name",
        "card_frog_helmet_description",
        "card_frog_helmet_name",
        "card_frog_man_description",
        "card_frog_man_name",
        "card_ghost_description",
        "card_ghost_name",
        "card_giant_snail_description",
        "card_giant_snail_name",
        "card_goblin_archer_description",
        "card_goblin_archer_name",
        "card_goblin_hat_description",
        "card_goblin_hat_name",
        "card_goblin_shaman_description",
        "card_goblin_shaman_name",
        "card_gold_chestplate_description",
        "card_gold_chestplate_name",
        "card_hammer_description",
        "card_hammer_name",
        "card_helmet_description",
        "card_helmet_name",
        "card_horned_helmet_description",
        "card_horned_helmet_name",
        "card_iron_shield_description",
        "card_iron_shield_name",
        "card_kraken_tooth_axe_description",
        "card_kraken_tooth_axe_name",
        "card_leather_tunic_description",
        "card_leather_tunic_name",
        "card_lumberjack_description",
        "card_lumberjack_name",
        "card_mage_description",
        "card_mage_name",
        "card_magic_blade_description",
        "card_magic_blade_name",
        "card_magic_broom_description",
        "card_magic_broom_name",
        "card_magic_dust_description",
        "card_magic_dust_name",
        "card_magic_ring_description",
        "card_magic_ring_name",
        "card_magic_staff_description",
        "card_magic_staff_name",
        "card_magic_tome_description",
        "card_magic_tome_name",
        "card_magic_wand_description",
        "card_magic_wand_name",
        "card_merman_description",
        "card_merman_name",
        "card_mimic_description",
        "card_mimic_name",
        "card_miner_description",
        "card_miner_name",
        "card_morning_star_description",
        "card_morning_star_name",
        "card_mosquito_description",
        "card_mosquito_name",
        "card_ninja_description",
        "card_ninja_name",
        "card_ogre_description",
        "card_ogre_name",
        "card_orc_wizard_description",
        "card_orc_wizard_name",
        "card_pickaxe_description",
        "card_pickaxe_name",
        "card_pirate_hat_description",
        "card_pirate_hat_name",
        "card_pirate_sword_description",
        "card_pirate_sword_name",
        "card_quiver_description",
        "card_quiver_name",
        "card_rat_crown_description",
        "card_rat_crown_name",
        "card_skull_helmet_description",
        "card_skull_helmet_name",
        "card_slingshot_description",
        "card_slingshot_name",
        "card_smithy_description",
        "card_smithy_name",
        "card_spiked_plank_description",
        "card_spiked_plank_name",
        "card_stable_portal_name",
        "card_stable_portal_status",
        "card_staff_of_fear_description",
        "card_staff_of_fear_name",
        "card_strange_portal_description",
        "card_strange_portal_name",
        "card_throwing_star_description",
        "card_throwing_star_name",
        "card_tiger_fur_coat_description",
        "card_tiger_fur_coat_name",
        "card_warrior_description",
        "card_warrior_name",
        "card_wicked_witch_description",
        "card_wicked_witch_name",
        "card_wicked_witch_name_2",
        "card_wizard_description",
        "card_wizard_name",
        "card_wizard_robe_description",
        "card_wizard_robe_name",
        "card_wolf_head_description",
        "card_wolf_head_name",
        "card_wooden_shield_description",
        "card_wooden_shield_name",
        "cardtype_equipable",
        "control_toggle_inventory",
        "credits_wouter",
        "defence_veryweak",
        "defence_weak",
        "defence_normal",
        "defence_strong",
        "defence_verystrong",
        "defence_extremelystrong",
        "hitchance_verysmall",
        "hitchance_small",
        "hitchance_normal",
        "hitchance_high",
        "hitchance_veryhigh",
        "hitchance_extremelyhigh",
        "idea_amulet_of_forest_status_0",
        "idea_amulet_of_mountain_status_0",
        "idea_axe_status_0",
        "idea_blowpipe_status_0",
        "idea_blunderbuss_status_0",
        "idea_bone_spear_status_0",
        "idea_bone_staff_status_0",
        "idea_boomerang_status_0",
        "idea_bow_status_0",
        "idea_broken_bottle_status_0",
        "idea_chainmail_armor_status_0",
        "idea_club_status_0",
        "idea_crossbow_status_0",
        "idea_gold_chestplate_status_0",
        "idea_growth_status_12",
        "idea_hammer_status_0",
        "idea_iron_shield_status_0",
        "idea_magic_blade_status_0",
        "idea_magic_ring_status_0",
        "idea_magic_staff_status_0",
        "idea_magic_tome_status_0",
        "idea_magic_wand_status_0",
        "idea_pickaxe_status_0",
        "idea_slingshot_status_0",
        "idea_smithy_status_0",
        "idea_spiked_plank_status_0",
        "idea_stable_portal_status_0",
        "idea_throwing_star_status_0",
        "idea_wizard_robe_status_0",
        "idea_wooden_shield_status_0",
        "label_base_combatlevel",
        "label_can_drop",
        "label_cancel_the_ritual",
        "label_combatlevel",
        "label_debug_cards",
        "label_debug_coin_chest",
        "label_debug_effects",
        "label_debug_end_moon",
        "label_debug_endless_moon",
        "label_debug_general",
        "label_debug_reset_run",
        "label_debug_scenario_demon",
        "label_debug_scenario_demon_lord",
        "label_debug_scenario_island",
        "label_debug_scenario_kraken",
        "label_debug_scenario_witch_forest",
        "label_debug_shortcut_copy",
        "label_debug_shortcut_delete",
        "label_debug_shortcut_heal",
        "label_debug_shortcut_progress",
        "label_debug_shortcut_status",
        "label_debug_shortcuts",
        "label_debug_spawn_enemies",
        "label_debug_toggle_no_food",
        "label_debug_toggle_peaceful_mode",
        "label_debug_unlock_boosters",
        "label_debug_unlock_ideas",
        "label_debug_unlock_quests",
        "label_defence",
        "label_demo",
        "label_demo_any_key_to_start",
        "label_demo_reset_warning",
        "label_equiping",
        "label_everyone_in_forest_dead",
        "label_everyone_in_forest_dead_text",
        "label_extra_combat_stats",
        "label_forest_fight",
        "label_forest_fight_wave_10",
        "label_forest_intro_1",
        "label_forest_intro_2",
        "label_forest_intro_3",
        "label_forest_intro_4",
        "label_forest_intro_5",
        "label_forest_intro_6",
        "label_forest_intro_title",
        "label_forest_leave",
        "label_forest_lost",
        "label_forest_lost_2",
        "label_forest_lost_title",
        "label_forest_resume",
        "label_forest_resume_title",
        "label_forest_wave_10_end",
        "label_forest_wave_10_end2",
        "label_forest_wave_end",
        "label_forest_wave_end_leave",
        "label_forest_wave_end_next_wave",
        "label_forest_wave_end_wave_10",
        "label_forest_wave_end2",
        "label_forest_wave_endless_end",
        "label_forest_wave_endless_end3",
        "label_forest_wave_title",
        "label_framerate_120",
        "label_framerate_30",
        "label_framerate_60",
        "label_framerate_cap",
        "label_framerate_unlimited",
        "label_go_to_forest_prompt",
        "label_inventory",
        "label_not_enough_food_before_portal",
        "label_taking_portal_full",
        "label_taking_portal_title",
        "label_toggle_inventory",
        "label_total_combatlevel",
        "quest_break_bottle_text",
        "quest_build_smithy_text",
        "quest_build_stable_portal_text",
        "quest_craft_amulet_forest_text",
        "quest_equip_archer_quiver_text",
        "quest_fight_wave_six_text",
        "quest_fight_wicked_witch_text",
        "quest_find_dark_forest_text",
        "quest_finish_first_wave_text",
        "quest_plant_berry_bush_text",
        "quest_punch_rock_text",
        "quest_punch_tree_text",
        "quest_train_archer_text",
        "quest_train_ninja_text",
        "quest_train_wizard_text",
        "quest_villager_combat_20_text",
        "quest_wear_bunny_hat_text",
        "quest_wear_crab_scale_armor_text",
        "questgroup_equipment",
        "questgroup_forest_mainquest",
        "rumor_combat_description",
        "rumor_combat_name",
        "specialhit_bleeding_long",
        "specialhit_crit_long",
        "specialhit_damage_long",
        "specialhit_frenzy_long",
        "specialhit_heal_long",
        "specialhit_heallowest_long",
        "specialhit_invulnerable_long",
        "specialhit_lifesteal_long",
        "specialhit_poison_long",
        "specialhit_stun_long",
        "statuseffect_bleeding_description",
        "statuseffect_bleeding_lore",
        "statuseffect_bleeding_name",
        "statuseffect_frenzy_description",
        "statuseffect_frenzy_lore",
        "statuseffect_frenzy_name",
        "statuseffect_invulnerable_description",
        "statuseffect_invulnerable_lore",
        "statuseffect_invulnerable_name",
        "target_allenemy",
        "target_allfriendly",
        "target_randomenemy",
        "target_randomfriendly",
        "target_self",
        "target_target",
        "cardtype_humans",
        "label_food_infobox",
        "label_food_infobox_warning",
        "label_starving_humans",
        "card_tuna_description",
        "card_cod_description",
        "card_mackerel_description",
        "label_health",
        "label_wave",
        "label_undiscovered_cards_tooltip",
        "label_undiscovered_cards_tooltip_title",
        "rumor_dark_forest_name",
        "rumor_dark_forest_description",
        "pack_equipment_text",
        "label_ui_scale",
        "label_ui_scale_100",
        "label_ui_scale_80",
        "label_ui_scale_60",
        "pack_combat_intro_text",
        "label_strange_portal_appeared_strong",
        "label_itemlevel",
        "label_health_info",
        "card_rare_portal_name",
        "card_rare_portal_description",
        "label_forest_wave_endless_end2",
        "label_max_villager_in_portal",
        "card_stable_portal_description",
        "label_update_title_forest",
        "label_update_text_forest",
        "card_militia_description",
        "card_swordsman_description",
        "quest_pause_game_text",
        "card_university_name",
        "card_university_description_long",
        "card_university_description_completed",
        "idea_university_status_0",
        "label_invention_fullname",
        "card_lighthouse_name",
        "card_lighthouse_description",
        "idea_lighthouse_status_0",
        "card_resource_chest_name_override",
        "card_resource_chest_name",
        "card_resource_chest_description",
        "card_resource_chest_description_long",
        "idea_resourcechest_status_0",
        "card_resource_magnet_name",
        "card_resource_magnet_name_override",
        "card_resource_magnet_description",
        "card_resource_magnet_description_long",
        "idea_resource_magnet_status_0",
        "card_heavy_foundation_name",
        "card_heavy_foundation_description",
        "idea_heavy_foundation_status_0",
        "card_conveyor_name",
        "card_conveyor_description",
        "card_conveyor_status",
        "idea_conveyor_status_0",
        "card_hotpot_name",
        "card_hotpot_description",
        "idea_hotpot_status_0",
        "card_trash_can_name",
        "card_trash_can_description",
        "idea_trash_can_status_0",
        "card_trash_can_status_0",
        "label_update_text_chaos",
        "label_update_title_chaos",
        "label_menu_sub_title",
        "card_breeding_pen_name",
        "card_breeding_pen_description",
        "idea_breedingpen_status_0",
        "action_breeding_status",
        "action_slaughtering_status",
        "card_slaughter_house_name",
        "card_slaughter_house_description",
        "idea_slaughterhouse_status_0",
        "card_wishing_well_name",
        "card_wishing_well_description_long",
        "card_wishing_well_wish_1",
        "card_wishing_well_wish_2",
        "card_wishing_well_wish_5",
        "card_wishing_well_wish_10",
        "card_wishing_well_wish_20",
        "card_wishing_well_wish_50",
        "idea_wishing_well_status_0",
        "card_brickyard_status",
        "card_sawmill_status",
        "label_one_villager_needs_to_stay_island",
        "card_university_status",
        "card_altar_description",
        "card_altar_name",
        "card_angry_royal_description",
        "card_angry_royal_name",
        "card_animal_cage_description",
        "card_animal_cage_name",
        "card_animal_cage_status_0",
        "card_animal_eating_status",
        "card_animal_old_name",
        "card_animal_pen_status",
        "card_baby_dragon_description",
        "card_baby_dragon_name",
        "card_barrel_description",
        "card_barrel_name",
        "card_barrel_status_0",
        "card_beer_description",
        "card_beer_name",
        "card_beer_status_0",
        "card_book_description",
        "card_book_name",
        "card_book_status_0",
        "card_bread_description",
        "card_bread_name",
        "card_bread_status_0",
        "card_cat_description",
        "card_cat_name",
        "card_charity_description",
        "card_charity_name",
        "card_charity_status_0",
        "card_charity_status_active",
        "card_cheese_description",
        "card_cheese_name",
        "card_cheese_status_0",
        "card_corpse_name_long",
        "card_corpse_remove",
        "card_crown_description",
        "card_crown_name",
        "card_crown_status_0",
        "card_curse_happiness_description",
        "card_death_curse_description",
        "card_death_curse_name",
        "card_death_recipe_description",
        "card_death_recipe_name",
        "card_death_spirit_description",
        "card_death_spirit_name",
        "card_display_spirit_dlc_description",
        "card_display_spirit_dlc_name",
        "card_dough_description",
        "card_dough_name",
        "card_dough_status_0",
        "card_dragon_egg_description",
        "card_dragon_egg_name",
        "card_dragon_egg_name_cracked",
        "card_dragon_scale_armor_description",
        "card_dragon_scale_armor_name",
        "card_euphoria_description",
        "card_euphoria_name",
        "card_euphoria_status_0",
        "card_fiend_description",
        "card_fiend_name",
        "card_fish_chips_description",
        "card_fish_chips_name",
        "card_fish_chips_status_0",
        "card_flour_description",
        "card_flour_mill_description",
        "card_flour_mill_name",
        "card_flour_name",
        "card_fountain_of_youth_description",
        "card_fountain_of_youth_name",
        "card_fountain_of_youth_status_0",
        "card_french_fries_description",
        "card_french_fries_name",
        "card_french_fries_status_0",
        "card_ghoul_description",
        "card_ghoul_name",
        "card_grape_description",
        "card_grape_name",
        "card_grape_pulp_description",
        "card_grape_pulp_name",
        "card_grape_pulp_status_0",
        "card_grape_vine_description",
        "card_grape_vine_name",
        "card_grape_vine_status",
        "card_greed_curse_description",
        "card_greed_curse_name",
        "card_greed_recipe_description",
        "card_greed_recipe_name",
        "card_greed_spirit_description",
        "card_greed_spirit_name",
        "card_happiness_curse_description",
        "card_happiness_curse_name",
        "card_happiness_description",
        "card_happiness_name",
        "card_happiness_recipe_description",
        "card_happiness_recipe_name",
        "card_happiness_spirit_description",
        "card_happiness_spirit_name",
        "card_herbal_tea_description",
        "card_herbal_tea_name",
        "card_herbal_tea_status_0",
        "card_herbal_tea_status_1",
        "card_herbs_description",
        "card_herbs_name",
        "card_hop_plant_status_0",
        "card_horse_description",
        "card_horse_name",
        "card_human_poop_description",
        "card_human_poop_name",
        "card_imp_description",
        "card_imp_name",
        "card_jester_description",
        "card_jester_hat_description",
        "card_jester_hat_name",
        "card_jester_hat_status_0",
        "card_jester_name",
        "card_kitten_description",
        "card_kitten_name",
        "card_merchant_description",
        "card_merchant_description_2",
        "card_merchant_name",
        "card_museum_description",
        "card_museum_name",
        "card_museum_status_0",
        "card_naming_stone_description",
        "card_naming_stone_name",
        "card_naming_stone_status_0",
        "card_old_cat_description",
        "card_old_cat_name",
        "card_old_dog_description",
        "card_old_dog_name",
        "card_old_villager_description",
        "card_old_villager_name",
        "card_olive_description",
        "card_olive_name",
        "card_olive_oil_description",
        "card_olive_oil_name",
        "card_olive_oil_status_0",
        "card_olive_pulp_description",
        "card_olive_pulp_name",
        "card_olive_pulp_status_0",
        "card_olive_tree_description",
        "card_olive_tree_name",
        "card_olive_tree_status",
        "card_outhouse_description",
        "card_outhouse_name",
        "card_outhouse_remove_poop",
        "card_outhouse_status_0",
        "card_oven_description",
        "card_oven_name",
        "card_painting_description",
        "card_painting_name",
        "card_painting_status_0",
        "card_pancakes_description",
        "card_pancakes_name",
        "card_pancakes_status_0",
        "card_paper_description",
        "card_paper_name",
        "card_paper_status_0",
        "card_petting_zoo_description",
        "card_petting_zoo_name",
        "card_petting_zoo_status_0",
        "card_petting_zoo_status_active",
        "card_pizza_description",
        "card_pizza_name",
        "card_pizza_status_0",
        "card_plague_mask_description",
        "card_plague_mask_name",
        "card_plague_mask_status_0",
        "card_poop_cant_sell",
        "card_poop_slime_description",
        "card_poop_slime_name",
        "card_possessed_blade_description",
        "card_possessed_blade_name",
        "card_puppy_description",
        "card_puppy_name",
        "card_rag_description",
        "card_rag_name",
        "card_roasted_fish_description",
        "card_roasted_fish_name",
        "card_roasted_fish_status_0",
        "card_roasted_meat_description",
        "card_roasted_meat_name",
        "card_roasted_meat_status_0",
        "card_royal_archer_description",
        "card_royal_archer_name",
        "card_royal_banquet_description",
        "card_royal_banquet_name",
        "card_royal_banquet_status_0",
        "card_royal_crown_description",
        "card_royal_crown_name",
        "card_royal_description",
        "card_royal_description_demand_2",
        "card_royal_guard_description",
        "card_royal_guard_name",
        "card_royal_mage_description",
        "card_royal_mage_name",
        "card_royal_name",
        "card_royal_tunic_description",
        "card_royal_tunic_name",
        "card_ruins_description",
        "card_ruins_name",
        "card_ruins_status",
        "card_sadness_demon_description",
        "card_sadness_demon_name",
        "card_scythe_description",
        "card_scythe_name",
        "card_scythe_status_0",
        "card_sewer_description",
        "card_sewer_name",
        "card_sewer_status_0",
        "card_shaman_description",
        "card_shaman_name",
        "card_shaman_status",
        "card_spirit_status_1",
        "card_spring_description",
        "card_spring_name",
        "card_squire_description",
        "card_squire_name",
        "card_squire_tunic_description",
        "card_squire_tunic_name",
        "card_squire_tunic_status_0",
        "card_stomping_vat_description",
        "card_stomping_vat_name",
        "card_stomping_vat_status_0",
        "card_tavern_description",
        "card_tavern_name",
        "card_tavern_status_0",
        "card_teenage_villager_description",
        "card_teenage_villager_name",
        "card_throwing_tomatos_description",
        "card_throwing_tomatos_name",
        "card_throwing_tomatos_status_0",
        "card_tomato_description",
        "card_tomato_name",
        "card_tomato_plant_description",
        "card_tomato_plant_name",
        "card_tomato_plant_status",
        "card_unhappiness_description",
        "card_unhappiness_name",
        "card_university_description",
        "card_water_description",
        "card_water_name",
        "card_water_status_0",
        "card_wheat_description",
        "card_wheat_name",
        "card_whip_description",
        "card_whip_name",
        "card_wine_description",
        "card_wine_name",
        "card_wine_status_0",
        "card_winter_coat_description",
        "card_winter_coat_name",
        "card_winter_coat_status_0",
        "card_wishing_well_description",
        "card_wool_dress_description",
        "card_wool_dress_name",
        "card_wool_dress_status_0",
        "card_wool_socks_description",
        "card_wool_socks_name",
        "card_wool_socks_status_0",
        "cardtype_happiness",
        "cardtype_spirits",
        "credits_cyber",
        "cursetype_death",
        "cursetype_greed",
        "cursetype_happiness",
        "cutscene_death_end_text_0",
        "cutscene_death_end_text_1",
        "cutscene_death_middle_text_0",
        "cutscene_death_middle_text_1",
        "cutscene_death_middle_text_2",
        "cutscene_greed_end_text_0",
        "cutscene_greed_middle_text_0",
        "cutscene_greed_middle_text_1",
        "cutscene_happiness_end_text_0",
        "cutscene_happiness_end_text_1",
        "cutscene_happiness_end_text_2",
        "cutscene_happiness_middle_text_1",
        "demand_fancy_dress_start_text",
        "demand_fancy_dress_success_text",
        "greed_quest_demand_description_not_found",
        "greed_quest_demand_failed",
        "greed_quest_demand_failed_2",
        "greed_quest_demand_failed_3",
        "greed_quest_demand_success",
        "greed_quest_demand_success_2",
        "greed_quest_demand_success_3",
        "greed_quest_demand_title",
        "idea_altar_status_0",
        "idea_death_curse_fix_description",
        "idea_death_curse_fix_name",
        "idea_death_curse_fix_status_0",
        "idea_flour_mill_status_0",
        "idea_flour_status_0",
        "idea_greed_curse_fix_description",
        "idea_greed_curse_fix_name",
        "idea_greed_curse_fix_status_0",
        "idea_growth_status_13",
        "idea_growth_status_14",
        "idea_growth_status_15",
        "idea_growth_status_16",
        "idea_growth_status_17",
        "idea_growth_status_18",
        "idea_happiness_curse_fix_description",
        "idea_happiness_curse_fix_name",
        "idea_happiness_curse_fix_status_0",
        "idea_happiness_description",
        "idea_happiness_name",
        "idea_happiness_result",
        "idea_happiness_status_0",
        "idea_happiness_status_1",
        "idea_offspring_status_2",
        "idea_oven_status_0",
        "idea_remove_happiness",
        "idea_tavern_status_0",
        "idea_unhappiness_status_0",
        "ideagroup_death",
        "ideagroup_greed",
        "ideagroup_happiness",
        "label_advanced_combat",
        "label_advanced_settings",
        "label_age_villagers",
        "label_altar_cutscene_help_false",
        "label_altar_cutscene_help_spirit_false",
        "label_altar_cutscene_help_spirit_true",
        "label_altar_cutscene_help_true",
        "label_altar_cutscene_text",
        "label_altar_cutscene_title",
        "label_angry_villager",
        "label_beat_curse_to_unlock",
        "label_buy_dlc_steam",
        "label_cardopedia_all",
        "label_cardopedia_forest",
        "label_cardopedia_island",
        "label_cardopedia_main",
        "label_cardopedia_modded",
        "label_cardopedia_order",
        "label_cardopedia_spirit",
        "label_change_board_disabled_text",
        "label_change_board_disabled_title",
        "label_clicktodrag_enabled",
        "label_clicktodrag_tooltip",
        "label_death_intro_1",
        "label_death_intro_2",
        "label_death_intro_3",
        "label_death_intro_4",
        "label_death_intro_5",
        "label_death_intro_title",
        "label_demand_collected",
        "label_demand_collected_2",
        "label_demand_complete_start",
        "label_enable_curse_unknown",
        "label_enable_death_curse",
        "label_enable_greed_curse",
        "label_enable_happiness_curse",
        "label_enabled_curses",
        "label_everyone_angry",
        "label_everyone_spirit_world_dead",
        "label_everyone_spirit_world_dead_text",
        "label_everyone_spirit_world_dead_text_retry",
        "label_final_demand_end_text",
        "label_final_demand_end_text_2",
        "label_final_demand_end_text_3",
        "label_final_demand_end_text_4",
        "label_final_demand_end_text_5",
        "label_final_demand_end_text_6",
        "label_final_demand_end_text_7",
        "label_final_demand_end_text_8",
        "label_final_demand_merchant",
        "label_final_demand_text",
        "label_final_demand_text_2",
        "label_final_demand_text_3",
        "label_final_demand_text_4",
        "label_forest_update",
        "label_fountain_text",
        "label_fountain_title",
        "label_giving_happiness",
        "label_greed_demand_failed_fight",
        "label_greed_demand_failed_first_time",
        "label_greed_intro_1",
        "label_greed_intro_2",
        "label_greed_intro_3",
        "label_greed_intro_4",
        "label_greed_intro_5",
        "label_greed_intro_title",
        "label_greed_lift_curse",
        "label_greed_lift_curse_2",
        "label_greed_lift_curse_3",
        "label_greed_lift_curse_kill_royal",
        "label_greed_new_villager",
        "label_greed_new_villager_2",
        "label_greed_outro_wear_crown",
        "label_happiness_infobox",
        "label_happiness_infobox_warning",
        "label_happiness_intro_1",
        "label_happiness_intro_2",
        "label_happiness_intro_3",
        "label_happiness_intro_4",
        "label_happiness_intro_5",
        "label_happiness_intro_title",
        "label_happiness_return_0",
        "label_happiness_warning",
        "label_island_update",
        "label_its_the_spirit",
        "label_magic_description",
        "label_magic_lore",
        "label_magic_title",
        "label_main_game",
        "label_melee_description",
        "label_melee_lore",
        "label_melee_title",
        "label_menu_spirit_title",
        "label_menu_spirit_title_locked",
        "label_missing_cards_text",
        "label_missing_cards_title",
        "label_mod_update_type",
        "label_mods",
        "label_mods_enable_title",
        "label_name_villager_text",
        "label_new_villager",
        "label_new_villager_death",
        "label_new_villager_happiness",
        "label_not_everyone_happy",
        "label_open_workshop",
        "label_random_name",
        "label_ranged_description",
        "label_ranged_lore",
        "label_ranged_title",
        "label_return_from_spirit_world_text",
        "label_return_from_spirit_world_title",
        "label_sadness_demon_text",
        "label_sadness_demon_title",
        "label_screenshake_enabled",
        "label_shaman_appeared",
        "label_shaman_intro",
        "label_shaman_leaving_text",
        "label_shaman_leaving_title",
        "label_spirit_dlc_not_installed_text",
        "label_spirit_dlc_not_installed_title",
        "label_spirit_outro_1",
        "label_spirit_outro_2",
        "label_spirit_outro_3",
        "label_spirit_outro_4",
        "label_spirit_outro_choice_0",
        "label_spirit_outro_choice_1",
        "label_spirit_update",
        "label_time_infobox",
        "label_try_attack_royal_description",
        "label_try_attack_royal_description_4",
        "label_try_attack_royal_description_8",
        "label_try_attack_royal_title",
        "label_update_text_spirit",
        "label_update_text_spirit_locked",
        "label_update_title_spirit",
        "label_villager_age_birthday",
        "label_villager_age_description",
        "label_villager_food_poisoning",
        "label_villager_old",
        "label_villager_old_age_death",
        "label_villager_sick",
        "label_villager_young",
        "label_wow",
        "pack_death_animals_text",
        "pack_death_basic_text",
        "pack_death_ideas_1_text",
        "pack_death_ideas_2_text",
        "pack_death_intro_text",
        "pack_death_locations_text",
        "pack_greed_basic1_text",
        "pack_greed_food_creatures_text",
        "pack_greed_ideas1_text",
        "pack_greed_ideas2_text",
        "pack_greed_intro_text",
        "pack_greed_luxuries_text",
        "pack_happiness_creatures_text",
        "pack_happiness_food_text",
        "pack_happiness_ideas1_text",
        "pack_happiness_ideas2_text",
        "pack_happiness_intro_text",
        "pack_happiness1_text",
        "quest_3_succesfull_demands_text",
        "quest_5_succesfull_demands_text",
        "quest_8_succesfull_demands_text",
        "quest_create_altar_text",
        "quest_death_befriend_cat_text",
        "quest_death_breed_cow_text",
        "quest_death_build_lumbercamp_text",
        "quest_death_build_outhouse_text",
        "quest_death_create_fountain_of_youth_text",
        "quest_death_cure_sick_villager_text",
        "quest_death_explore_ruins_text",
        "quest_death_find_cure_text",
        "quest_death_find_fix_text",
        "quest_death_have_3_cows_text",
        "quest_death_have_3_poop_text",
        "quest_death_make_cheese_text",
        "quest_death_name_villager_text",
        "quest_death_second_villager_text",
        "quest_death_third_villager_text",
        "quest_death_unlock_packs_text",
        "quest_death_villager_old_age_dead_text",
        "quest_death_villager_old_text",
        "quest_enter_death_world_text",
        "quest_enter_greed_world_text",
        "quest_enter_happiness_world_text",
        "quest_fight_royal_guard_text",
        "quest_find_death_world_text",
        "quest_find_greed_world_text",
        "quest_find_happiness_world_text",
        "quest_first_demand_text",
        "quest_get_grape_text",
        "quest_greed_brickyard_text",
        "quest_greed_find_fix_text",
        "quest_greed_garden_text",
        "quest_greed_lumbercamp_text",
        "quest_greed_mine_text",
        "quest_greed_oak_barrel_text",
        "quest_greed_olive_oil_text",
        "quest_greed_quarry_text",
        "quest_greed_roasted_meat_text",
        "quest_greed_sawmill_text",
        "quest_greed_smelter_text",
        "quest_greed_stomping_vat_text",
        "quest_greed_wine_text",
        "quest_greed_wool_text",
        "quest_happiness_admire_a_coin_text",
        "quest_happiness_all_packs_text",
        "quest_happiness_bake_bread_text",
        "quest_happiness_bake_pizza_text",
        "quest_happiness_build_charity_text",
        "quest_happiness_build_garden_text",
        "quest_happiness_build_museum_text",
        "quest_happiness_build_tavern_text",
        "quest_happiness_create_flour_text",
        "quest_happiness_find_fix_text",
        "quest_happiness_get_2_happiness_text",
        "quest_happiness_have_1_unhappiness_text",
        "quest_happiness_have_10_unhappiness_text",
        "quest_happiness_have_5_unhappiness_text",
        "quest_happiness_make_dough_text",
        "quest_open_death_intro_pack_text",
        "quest_open_happiness_intro_pack_text",
        "quest_open_pack_text",
        "questgroup_death_mainquest",
        "questgroup_death_misc",
        "questgroup_death_starter",
        "questgroup_discover_spirits",
        "questgroup_greed_mainquest",
        "questgroup_greed_misc",
        "questgroup_greed_starter",
        "questgroup_greed_thriving",
        "questgroup_happiness_collecting",
        "questgroup_happiness_cooking",
        "questgroup_happiness_mainquest",
        "questgroup_happiness_starter",
        "questgroup_happiness_unhappy",
        "specialhit_anxious_long",
        "statuseffect_angry_description",
        "statuseffect_angry_lore",
        "statuseffect_angry_name",
        "statuseffect_anxious_description",
        "statuseffect_anxious_lore",
        "statuseffect_anxious_name",
        "statuseffect_demand_description",
        "statuseffect_demand_lore",
        "statuseffect_demand_name",
        "statuseffect_sick_description",
        "statuseffect_sick_lore",
        "statuseffect_sick_name",
        "label_shaman_intro_demon",
        "label_shaman_intro_island",
        "label_beta_thanks",
        "label_beta_text",
        "label_shaman_intro_cursed",
        "label_shaman_intro_title",
        "card_cursed_wand_name",
        "card_cursed_wand_description",
        "label_demand_coins_text",
        "label_demand_garden_text",
        "label_demand_olives_text",
        "label_demand_beer_text",
        "label_demand_fancy_dress_text",
        "label_demand_royal_banquet_text",
        "label_demand_wool_socks_text",
        "label_demand_wine_text",
        "label_demand_painting_text",
        "label_missing_cards_more_text",
        "label_animal_die",
        "specialhit_sick_long",
        "card_well_name",
        "card_well_description",
        "card_well_status_0",
        "card_well_status_1",
        "label_disable_paused_text",
        "label_placeholder_search",
        "label_conflict_very_effective",
        "cutscene_happiness_food_text_0",
        "cutscene_happiness_food_text_1",
        "label_altar_cutscene_mainland",
        "label_altar_run_board",
        "label_altar_run_redo",
        "board_island_name",
        "board_main_name",
        "board_forest_name",
        "board_greed_name",
        "board_death_name",
        "board_happiness_name",
        "label_altar_cutscene_good_luck",
        "cutscene_happiness_middle_text_0",
        "label_name_villager_title",
        "credits_tumult",
        "label_spirit_outro_0_greed",
        "label_spirit_outro_0_death",
        "label_spirit_outro_0_happiness",
        "card_sad_event_description",
        "card_sad_event_name",
        "label_sad_event_appeared",
        "label_greed_demand_failed_fight_peaceful",
        "label_shaman_intro_peaceful",
        "card_archer_name_young",
        "card_archer_name_old",
        "card_builder_name_young",
        "card_builder_name_old",
        "card_lumberjack_name_young",
        "card_lumberjack_name_old",
        "card_mage_name_young",
        "card_mage_name_old",
        "card_miner_name_young",
        "card_miner_name_old",
        "card_ninja_name_young",
        "card_ninja_name_old",
        "card_warrior_name_young",
        "card_warrior_name_old",
        "card_wizard_name_young",
        "card_wizard_name_old",
        "card_explorer_name_young",
        "card_explorer_name_old",
        "card_militia_name_young",
        "card_militia_name_old",
        "card_swordsman_name_young",
        "card_swordsman_name_old",
        "card_fisher_name_young",
        "card_fisher_name_old",
        "card_friendly_pirate_name_young",
        "card_friendly_pirate_name_old",
        "card_trained_monkey_name_young",
        "card_trained_monkey_name_old",
        "card_jester_name_young",
        "card_jester_name_old",
        "label_youtube_dlc_title",
        "label_youtube_dlc_text",
        "label_load_run",
        "label_exit",
        "card_chicken_name_old",
        "card_cow_name_old",
        "card_crab_name_old",
        "card_horse_name_old",
        "card_monkey_name_old",
        "card_parrot_name_old",
        "card_rabbit_name_old",
        "card_sheep_name_old",
        "cutscene_death_middle_text_3",
        "cutscene_death_middle_text_4",
        "label_greed_given",
        "credits_betatesting",
        "quest_happiness_read_book_text",
        "label_music",
        "card_carriage_name",
        "card_carriage_description",
        "card_carriage_status_0",
        "card_carriage_status_1",
        "cutscene_expedition_start_title",
        "cutscene_expedition_start_text",
        "cutscene_expedition_start_text_1",
        "cutscene_expedition_start_text_2",
        "cutscene_expedition_board_start_text",
        "cutscene_expedition_board_start_text_1",
        "cutscene_expedition_board_start_text_2",
        "cutscene_expedition_board_start_title",
        "pack_draw_pack_text",
        "label_everyone_expedition_dead",
        "label_everyone_expedition_dead_text",
        "label_everyone_expedition_dead_text_retry"
      ]
    },
    "enum": {
      "CardType": [
        "Structures",
        "Humans",
        "Resources",
        "Ideas",
        "Food",
        "Mobs",
        "Locations",
        "Fish",
        "Rumors",
        "Equipable",
        "Spirits"
      ],
      "BlueprintGroup": [
        "Basic",
        "Building",
        "Military",
        "Cooking",
        "Resources",
        "Sailing",
        "Island",
        "Fishing",
        "Important",
        "Happiness",
        "Death",
        "Greed"
      ],
      "EnemySetCardBag": [
        "BasicEnemy",
        "AdvancedEnemy",
        "Island_BasicEnemy",
        "Island_AdvancedEnemy",
        "Forest_BasicEnemy",
        "Forest_AdvancedEnemy",
        "Happiness_Enemy"
      ],
      "SetCardBagType": [
        "BasicResources",
        "AdvancedResources",
        "SpecialResources",
        "BasicHarvestable",
        "BasicFood",
        "AdvancedFood",
        "Animal",
        "BasicEnemy",
        "AdvancedEnemy",
        "BasicIdea",
        "BasicBuildingIdea",
        "AdvancedBuildingIdea",
        "CookingIdea",
        "AdvancedHarvestable",
        "Island_BasicResources",
        "Island_BasicFood",
        "Island_BasicHarvestable",
        "Island_AdvancedHarvestable",
        "Island_Animal",
        "Island_BasicEnemy",
        "Island_BasicIdea",
        "Island_CookingIdea",
        "Island_AdvancedIdea",
        "Island_AdvancedFood",
        "Island_AdvancedResources",
        "Island_AdvancedEnemy",
        "Island_AdvancedBuildingIdea",
        "Forest_BasicEnemy",
        "Forest_AdvancedEnemy",
        "EquipmentBlueprints",
        "Happiness_BasicIdea",
        "Happiness_CookingIdea",
        "Happiness_BasicBuildingIdea",
        "Happiness_AdvancedBuildingIdea",
        "Happiness_Harvestable",
        "Happiness_Animal",
        "Greed_AdvancedIdea",
        "Greed_Animal",
        "Greed_BasicIdea",
        "Greed_Cooking",
        "Greed_Luxuries",
        "Greed_Harvestables",
        "Greed_Buildings",
        "Greed_Equipables",
        "Death_Harvestable",
        "Death_Animal",
        "Death_BasicIdea",
        "Death_AdvancedIdea",
        "Death_AdvancedResources",
        "Greed_RequiredBuildings",
        "Greed_BasicResources",
        "Greed_AdvancedResources",
        "Happiness_Enemy"
      ],
      "PickupSoundGroup": [
        "Default",
        "Medium",
        "Heavy",
        "Custom"
      ],
      "CardUpdateType": [
        "Main",
        "Island",
        "Spirit",
        "Forest",
        "Order",
        "Mod"
      ],
      "AttackType": [
        "None",
        "Melee",
        "Ranged",
        "Magic"
      ],
      "CurseType": [
        "Happiness",
        "Death",
        "Greed"
      ],
      "EquipableType": [
        "Head",
        "Torso",
        "Weapon"
      ],
      "Location": [
        "Mainland",
        "Island",
        "Forest",
        "Happiness",
        "Greed",
        "Death"
      ]
    }
  }
}